ck_widgets/__init__.py
ck_widgets/color/__init__.py
ck_widgets/color/color_tools.py
ck_widgets/examples/__init__.py
ck_widgets/examples/list_view.py
ck_widgets/examples/value_bar.py
ck_widgets/widgets/__init__.py
ck_widgets/widgets/debug_window.py
ck_widgets/widgets/list_view.py
ck_widgets/widgets/value_bar.py
ck_widgets-0.2.0.dist-info/LICENSE
ck_widgets-0.2.0.dist-info/METADATA
ck_widgets-0.2.0.dist-info/WHEEL
ck_widgets-0.2.0.dist-info/top_level.txt
ck_widgets-0.2.0.dist-info/RECORD
