Metadata-Version: 2.1
Name: ck-widgets
Version: 0.2.0
Summary: Package with widgets and components for Textual TUI Framework.
Home-page: http://github.com/Cvaniak/CvaniaksTextualWidgets
Author: Cvaniak
Author-email: igna.cwaniak@gmail.com
License: MIT
Platform: UNKNOWN
License-File: LICENSE
Requires-Dist: rich
Requires-Dist: textual
